tkcalendar2/__init__.py
tkcalendar2/tkcalendar.py
tkcalendar2-1.1.0.dist-info/LICENSE.txt
tkcalendar2-1.1.0.dist-info/METADATA
tkcalendar2-1.1.0.dist-info/WHEEL
tkcalendar2-1.1.0.dist-info/top_level.txt
tkcalendar2-1.1.0.dist-info/RECORD
