Metadata-Version: 2.1
Name: tkcalendar2
Version: 1.1.0
Summary: show a calendar in your tkinter application
Home-page: UNKNOWN
Author: Smart-Space
Author-email: smart-space@qq.com
License: MIT License
Platform: UNKNOWN
Classifier: Intended Audience :: Developers
Classifier: Operating System :: Microsoft :: Windows
Classifier: Programming Language :: Python
Classifier: License :: OSI Approved :: MIT License
Classifier: Topic :: Software Development :: Libraries
Requires-Python: >=3.6
License-File: LICENSE.txt
Requires-Dist: pythonnet
